AUTHORS
CHANGELOG.txt
DESCRIPTION
LICENSE
MANIFEST.in
README.md
requirements.txt
setup.cfg
setup.py
tox.ini
django_ember_toolkit/__init__.py
django_ember_toolkit/admin.py
django_ember_toolkit/models.py
django_ember_toolkit/urls.py
django_ember_toolkit/views.py
django_ember_toolkit.egg-info/PKG-INFO
django_ember_toolkit.egg-info/SOURCES.txt
django_ember_toolkit.egg-info/dependency_links.txt
django_ember_toolkit.egg-info/requires.txt
django_ember_toolkit.egg-info/top_level.txt
django_ember_toolkit/management/__init__.py
django_ember_toolkit/management/commands/__init__.py
django_ember_toolkit/management/commands/_base.py
django_ember_toolkit/management/commands/create_ember_project.py
django_ember_toolkit/management/commands/generate_ember_config.py
django_ember_toolkit/management/commands/generate_ember_models.py
django_ember_toolkit/management/commands/runserver_ember.py
django_ember_toolkit/static/.empty
django_ember_toolkit/static/django_ember_toolkit/.empty
django_ember_toolkit/templates/django_ember_toolkit/environment.js
django_ember_toolkit/templatetags/__init__.py
django_ember_toolkit/templatetags/django_ember_toolkit_tags.py
django_ember_toolkit/tests/.coveragerc
django_ember_toolkit/tests/__init__.py
django_ember_toolkit/tests/factories.py
django_ember_toolkit/tests/models_tests.py
django_ember_toolkit/tests/runtests.py
django_ember_toolkit/tests/south_settings.py
django_ember_toolkit/tests/test_settings.py
django_ember_toolkit/tests/urls.py
django_ember_toolkit/tests/test_app/__init__.py
django_ember_toolkit/tests/test_app/models.py
django_ember_toolkit/tests/test_app/templates/400.html
django_ember_toolkit/tests/test_app/templates/500.html