Metadata-Version: 1.0
Name: django-ember-toolkit
Version: 0.1
Summary: Tools to integrate develop an Ember app using Django as the backend.
